funnelweb
