Metadata-Version: 1.0
Name: funnelweb
Version: 1.1.1
Summary: Crawl and parse static sites and import to Plone
Home-page: http://pypi.python.org/pypi/funnelweb
Author: Dylan Jay
Author-email: software@pretaweb.com
License: GPL
Keywords: buildout crawler spider plone
Platform: UNKNOWN
Classifier: Framework :: Buildout
Classifier: Intended Audience :: Developers
Classifier: Topic :: Software Development :: Build Tools
Classifier: License :: OSI Approved :: Zope Public License
